pyopenvidu/__init__.py
pyopenvidu/exceptions.py
pyopenvidu/openvidu.py
pyopenvidu/openviduconnection.py
pyopenvidu/openvidupublisher.py
pyopenvidu/openvidusession.py
pyopenvidu/openvidusubscriber.py
pyopenvidu-0.2.1.dist-info/AUTHORS.rst
pyopenvidu-0.2.1.dist-info/LICENSE
pyopenvidu-0.2.1.dist-info/METADATA
pyopenvidu-0.2.1.dist-info/WHEEL
pyopenvidu-0.2.1.dist-info/top_level.txt
pyopenvidu-0.2.1.dist-info/RECORD
