Metadata-Version: 2.1
Name: pyopenvidu
Version: 0.2.1
Summary: Python interface to the OpenVidu WebRTC videoconference library.
Home-page: https://github.com/marcsello/pyopenvidu
Author: Marcell Pünkösd
Author-email: punkosdmarcell@rocketmail.com
License: MIT license
Project-URL: Documentation, https://pyopenvidu.readthedocs.io/
Project-URL: Code, https://github.com/marcsello/pyopenvidu
Project-URL: Issue tracker, https://github.com/marcsello/pyopenvidu/issues
Keywords: pyopenvidu
Platform: UNKNOWN
Classifier: Development Status :: 3 - Alpha
Classifier: Intended Audience :: Developers
Classifier: License :: OSI Approved :: MIT License
Classifier: Natural Language :: English
Classifier: Environment :: Web Environment
Classifier: Operating System :: OS Independent
Classifier: Topic :: Communications
Classifier: Topic :: Communications :: Conferencing
Classifier: Topic :: Software Development :: Libraries :: Python Modules
Classifier: Programming Language :: Python
Classifier: Programming Language :: Python :: 3
Classifier: Programming Language :: Python :: 3.7
Classifier: Programming Language :: Python :: 3.8
Classifier: Programming Language :: Python :: 3.9
Requires-Python: >=3.7
License-File: LICENSE
License-File: AUTHORS.rst
Requires-Dist: requests
Requires-Dist: requests-toolbelt
